{
  "css/chat_box.css": "css/chat_box-650090f271.css",
  "css/footer.css": "css/footer-e44a5088f1.css",
  "css/header.css": "css/header-7e66ce8ab7.css",
  "css/home.css": "css/home-125e3a7322.css",
  "css/layout.css": "css/layout-1c56739c13.css",
  "css/sign_in.css": "css/sign_in-adac1cbbe5.css",
  "css/sign_up.css": "css/sign_up-6df8476b12.css",
  "css/user.css": "css/user-8d569bb5ae.css",
  "js/chat_engine.js": "js/chat_engine-06290012f5.js",
  "js/home_comments.js": "js/home_comments-0eae35ff22.js",
  "js/home_posts.js": "js/home_posts-c5660f4f74.js"
}